dbrx_ops/__init__.py
dbrx_ops/errors.py
dbrx_ops/main.py
dbrx_ops/routes.py
dbrx_ops/s3.py
dbrx_ops/schemas.py
dbrx_ops/settings.py
dbrx_ops/monitoring/logger.py
dbrx_ops/s3/__init__.py
dbrx_ops/s3/delete_objects.py
dbrx_ops/s3/read_objects.py
dbrx_ops/s3/write_objects.py
dbrx_de_ops-0.0.0.dist-info/METADATA
dbrx_de_ops-0.0.0.dist-info/WHEEL
dbrx_de_ops-0.0.0.dist-info/top_level.txt
dbrx_de_ops-0.0.0.dist-info/RECORD
